jqgpt/__init__.py
jqgpt/main.py
jqgpt-0.1.1.dist-info/LICENSE
jqgpt-0.1.1.dist-info/METADATA
jqgpt-0.1.1.dist-info/WHEEL
jqgpt-0.1.1.dist-info/entry_points.txt
jqgpt-0.1.1.dist-info/top_level.txt
jqgpt-0.1.1.dist-info/RECORD
