Metadata-Version: 2.1
Name: jqgpt
Version: 0.1.1
Summary: jqgpt is a gpt powered tool that helps you write jq queries. It takes a human user query and a json file as input and outputs a jq query that answers the user query. It requires an OPENAI_API_KEY to work.
Home-page: https://github.com/ankushagarwal/jqgpt
Author: Ankush Agarwal
License: MIT
Requires-Python: >=3.6
License-File: LICENSE
Requires-Dist: openai
